collibra_protect_api_partner/__init__.py
collibra_protect_api_partner/api_client.py
collibra_protect_api_partner/configuration.py
collibra_protect_api_partner/rest.py
collibra_protect_api_partner/api/__init__.py
collibra_protect_api_partner/api/synchronizations_api.py
collibra_protect_api_partner/models/__init__.py
collibra_protect_api_partner/models/access.py
collibra_protect_api_partner/models/base_masking.py
collibra_protect_api_partner/models/constant_masking.py
collibra_protect_api_partner/models/custom_masking.py
collibra_protect_api_partner/models/data_access_rule_set.py
collibra_protect_api_partner/models/database.py
collibra_protect_api_partner/models/database_column.py
collibra_protect_api_partner/models/database_column_access_rule.py
collibra_protect_api_partner/models/database_column_tag.py
collibra_protect_api_partner/models/database_custom_masking.py
collibra_protect_api_partner/models/database_schema.py
collibra_protect_api_partner/models/database_table.py
collibra_protect_api_partner/models/database_table_access_rule.py
collibra_protect_api_partner/models/database_tag.py
collibra_protect_api_partner/models/default_masking.py
collibra_protect_api_partner/models/group_masking.py
collibra_protect_api_partner/models/hash_masking.py
collibra_protect_api_partner/models/masking.py
collibra_protect_api_partner/models/masking_mappings.py
collibra_protect_api_partner/models/masking_type.py
collibra_protect_api_partner/models/no_masking.py
collibra_protect_api_partner/models/provider.py
collibra_protect_api_partner/models/provider_details.py
collibra_protect_api_partner/models/row_filter.py
collibra_protect_api_partner/models/row_filter_operator.py
collibra_protect_api_partner/models/show_last_masking.py
collibra_protect_api_partner/models/standard_error_response.py
collibra_protect_api_partner/models/synchronization.py
test/__init__.py
test/test_access.py
test/test_base_masking.py
test/test_constant_masking.py
test/test_custom_masking.py
collibra_protect_api_partner-1.0.0.dist-info/METADATA
collibra_protect_api_partner-1.0.0.dist-info/WHEEL
collibra_protect_api_partner-1.0.0.dist-info/top_level.txt
collibra_protect_api_partner-1.0.0.dist-info/RECORD
