Metadata-Version: 2.1
Name: collibra-protect-api-partner
Version: 1.0.0
Summary: Collibra Protect API - Partner
Home-page: 
Author-email: 
Keywords: Swagger,Collibra Protect API - Partner
Requires-Dist: urllib3 (>=1.15)
Requires-Dist: six (>=1.10)
Requires-Dist: certifi
Requires-Dist: python-dateutil
